passagemath_giac/__init__.py
passagemath_giac.libs/libcliquer-8ee60577.so.1.0.21
passagemath_giac.libs/libcrypto-5ac4246e.so.3
passagemath_giac.libs/libcurl-23d58906.so.4.8.0
passagemath_giac.libs/libgfortran-83c28eba.so.5.0.0
passagemath_giac.libs/libgiac-498f1f2c.so.0.0.0
passagemath_giac.libs/libglpk-80d81766.so.40.3.1
passagemath_giac.libs/libgmp-6e109695.so.10.5.0
passagemath_giac.libs/libgsl-cda90e79.so.28.0.0
passagemath_giac.libs/libgslcblas-1f9534fd.so.0.0.0
passagemath_giac.libs/libmpfi-bcd96d8d.so.0.0.0
passagemath_giac.libs/libmpfr-104d25bb.so.6.2.2
passagemath_giac.libs/libopenblasp-r0-6dcb67f9.3.29.so
passagemath_giac.libs/libpari-gmp-tls-0f7c21c3.so.2.17.2
passagemath_giac.libs/libquadmath-2284e583.so.0.0.0
passagemath_giac.libs/libreadline-ea270e21.so.8.2
passagemath_giac.libs/libssl-deb203c8.so.3
passagemath_giac.libs/libtinfo-ceb117d9.so.6.3
sage/all__sagemath_giac.py
sage/interfaces/all__sagemath_giac.py
sage/interfaces/giac.py
sage/libs/all__sagemath_giac.py
sage/libs/giac/__init__.py
sage/libs/giac/auto-methods.pxi
sage/libs/giac/giac.cpython-310-x86_64-linux-gnu.so
sage/libs/giac/giac.pxd
sage/libs/giac/giac.pyx
sage/libs/giac/keywords.pxi
sage/libs/giac/misc.h
sage_wheels/bin/giac
passagemath_giac-10.6.43.dist-info/METADATA
passagemath_giac-10.6.43.dist-info/WHEEL
passagemath_giac-10.6.43.dist-info/top_level.txt
passagemath_giac-10.6.43.dist-info/RECORD
passagemath_giac-10.6.43.dist-info/sboms/auditwheel.cdx.json
